{
  "version": "1.0",
  "chainId": "146",
  "createdAt": 1764762383,
  "meta": {
    "name": "Transactions Batch",
    "description": "Weekly gauge rewards",
    "txBuilderVersion": "1.18.0",
    "createdFromSafeAddress": "0x97079F7E04B535FE7cD3f972Ce558412dFb33946",
    "createdFromOwnerAddress": "",
    "checksum": "0xfea43c482aab4a5993323fc70e869023974239c62641724d46c28ab9c98202c3"
  },
  "transactions": [
    {
      "to": "0x2d0e0814e62d80056181f5cd932274405966e4f0",
      "value": "0",
      "data": null,
      "contractMethod": {
        "inputs": [
          {
            "internalType": "address",
            "name": "spender",
            "type": "address"
          },
          {
            "internalType": "uint256",
            "name": "amount",
            "type": "uint256"
          }
        ],
        "name": "approve",
        "payable": false
      },
      "contractInputsValues": {
        "spender": "0xae647ea922d392cc825c51967382940a30893f6d",
        "amount": "117115000000000000000000"
      }
    },
    {
      "to": "0xae647ea922d392cc825c51967382940a30893f6d",
      "value": "0",
      "data": null,
      "contractMethod": {
        "inputs": [
          {
            "name": "_reward_token",
            "type": "address"
          },
          {
            "name": "_amount",
            "type": "uint256"
          }
        ],
        "name": "deposit_reward_token",
        "payable": false
      },
      "contractInputsValues": {
        "_reward_token": "0x2d0e0814e62d80056181f5cd932274405966e4f0",
        "_amount": "117115000000000000000000"
      }
    },
    {
      "to": "0x2d0e0814e62d80056181f5cd932274405966e4f0",
      "value": "0",
      "data": null,
      "contractMethod": {
        "inputs": [
          {
            "internalType": "address",
            "name": "spender",
            "type": "address"
          },
          {
            "internalType": "uint256",
            "name": "amount",
            "type": "uint256"
          }
        ],
        "name": "approve",
        "payable": false
      },
      "contractInputsValues": {
        "spender": "0x837c9ee0fb04897522ee48ae6c4d8040455defa8",
        "amount": "30693000000000000000000"
      }
    },
    {
      "to": "0x837c9ee0fb04897522ee48ae6c4d8040455defa8",
      "value": "0",
      "data": null,
      "contractMethod": {
        "inputs": [
          {
            "name": "_reward_token",
            "type": "address"
          },
          {
            "name": "_amount",
            "type": "uint256"
          }
        ],
        "name": "deposit_reward_token",
        "payable": false
      },
      "contractInputsValues": {
        "_reward_token": "0x2d0e0814e62d80056181f5cd932274405966e4f0",
        "_amount": "30693000000000000000000"
      }
    },
    {
      "to": "0xe5da20f15420ad15de0fa650600afc998bbe3955",
      "value": "0",
      "data": null,
      "contractMethod": {
        "inputs": [
          {
            "internalType": "address",
            "name": "spender",
            "type": "address"
          },
          {
            "internalType": "uint256",
            "name": "amount",
            "type": "uint256"
          }
        ],
        "name": "approve",
        "payable": false
      },
      "contractInputsValues": {
        "spender": "0x837c9ee0fb04897522ee48ae6c4d8040455defa8",
        "amount": "506580000000000000000"
      }
    },
    {
      "to": "0x837c9ee0fb04897522ee48ae6c4d8040455defa8",
      "value": "0",
      "data": null,
      "contractMethod": {
        "inputs": [
          {
            "name": "_reward_token",
            "type": "address"
          },
          {
            "name": "_amount",
            "type": "uint256"
          }
        ],
        "name": "deposit_reward_token",
        "payable": false
      },
      "contractInputsValues": {
        "_reward_token": "0xe5da20f15420ad15de0fa650600afc998bbe3955",
        "_amount": "506580000000000000000"
      }
    },
    {
      "to": "0x2d0e0814e62d80056181f5cd932274405966e4f0",
      "value": "0",
      "data": null,
      "contractMethod": {
        "inputs": [
          {
            "internalType": "address",
            "name": "spender",
            "type": "address"
          },
          {
            "internalType": "uint256",
            "name": "amount",
            "type": "uint256"
          }
        ],
        "name": "approve",
        "payable": false
      },
      "contractInputsValues": {
        "spender": "0xd3122266310f12a0afce319b5c0b20c8bfd51a1e",
        "amount": "21000000000000000000"
      }
    },
    {
      "to": "0xd3122266310f12a0afce319b5c0b20c8bfd51a1e",
      "value": "0",
      "data": null,
      "contractMethod": {
        "inputs": [
          {
            "name": "_reward_token",
            "type": "address"
          },
          {
            "name": "_amount",
            "type": "uint256"
          }
        ],
        "name": "deposit_reward_token",
        "payable": false
      },
      "contractInputsValues": {
        "_reward_token": "0x2d0e0814e62d80056181f5cd932274405966e4f0",
        "_amount": "21000000000000000000"
      }
    },
    {
      "to": "0x2d0e0814e62d80056181f5cd932274405966e4f0",
      "value": "0",
      "data": null,
      "contractMethod": {
        "inputs": [
          {
            "internalType": "address",
            "name": "spender",
            "type": "address"
          },
          {
            "internalType": "uint256",
            "name": "amount",
            "type": "uint256"
          }
        ],
        "name": "approve",
        "payable": false
      },
      "contractInputsValues": {
        "spender": "0x8cdc5eb34a3ac43e5f88bdae34b3c12b829d2b7e",
        "amount": "1554000000000000000000"
      }
    },
    {
      "to": "0x8cdc5eb34a3ac43e5f88bdae34b3c12b829d2b7e",
      "value": "0",
      "data": null,
      "contractMethod": {
        "inputs": [
          {
            "name": "_reward_token",
            "type": "address"
          },
          {
            "name": "_amount",
            "type": "uint256"
          }
        ],
        "name": "deposit_reward_token",
        "payable": false
      },
      "contractInputsValues": {
        "_reward_token": "0x2d0e0814e62d80056181f5cd932274405966e4f0",
        "_amount": "1554000000000000000000"
      }
    },
    {
      "to": "0x2d0e0814e62d80056181f5cd932274405966e4f0",
      "value": "0",
      "data": null,
      "contractMethod": {
        "inputs": [
          {
            "internalType": "address",
            "name": "spender",
            "type": "address"
          },
          {
            "internalType": "uint256",
            "name": "amount",
            "type": "uint256"
          }
        ],
        "name": "approve",
        "payable": false
      },
      "contractInputsValues": {
        "spender": "0xc4c97ec58e3024fddddd6173b663234eea6f27ae",
        "amount": "2436000000000000000000"
      }
    },
    {
      "to": "0xc4c97ec58e3024fddddd6173b663234eea6f27ae",
      "value": "0",
      "data": null,
      "contractMethod": {
        "inputs": [
          {
            "name": "_reward_token",
            "type": "address"
          },
          {
            "name": "_amount",
            "type": "uint256"
          }
        ],
        "name": "deposit_reward_token",
        "payable": false
      },
      "contractInputsValues": {
        "_reward_token": "0x2d0e0814e62d80056181f5cd932274405966e4f0",
        "_amount": "2436000000000000000000"
      }
    }
  ]
}