{
  "version": "1.0",
  "chainId": "146",
  "createdAt": 1748947636,
  "meta": {
    "name": "Transactions Batch",
    "description": "Withdrawing fees from the fee controller to 0x693f30c37D5a0Db9258C636E93Ccf011ACd8c90c",
    "txBuilderVersion": "1.18.0",
    "createdFromSafeAddress": "0x26377CAB961c84F2d7b9d9e36D296a1C1c77C995",
    "createdFromOwnerAddress": "",
    "checksum": "0xfea43c482aab4a5993323fc70e869023974239c62641724d46c28ab9c98202c3"
  },
  "transactions": [
    {
      "to": "0xa731C23D7c95436Baaae9D52782f966E1ed07cc8",
      "value": "0",
      "data": null,
      "contractMethod": {
        "inputs": [
          {
            "internalType": "address",
            "name": "pool",
            "type": "address"
          },
          {
            "internalType": "address",
            "name": "recipient",
            "type": "address"
          }
        ],
        "name": "withdrawProtocolFees",
        "payable": false
      },
      "contractInputsValues": {
        "pool": "0x8bcbb4d38cd3a81e8c682911ca74af983b663cac",
        "recipient": "0x693f30c37D5a0Db9258C636E93Ccf011ACd8c90c"
      }
    },
    {
      "to": "0xa731C23D7c95436Baaae9D52782f966E1ed07cc8",
      "value": "0",
      "data": null,
      "contractMethod": {
        "inputs": [
          {
            "internalType": "address",
            "name": "pool",
            "type": "address"
          },
          {
            "internalType": "address",
            "name": "recipient",
            "type": "address"
          }
        ],
        "name": "withdrawProtocolFees",
        "payable": false
      },
      "contractInputsValues": {
        "pool": "0x8dcea83145135d23f3b79ac926ceb3835730c087",
        "recipient": "0x693f30c37D5a0Db9258C636E93Ccf011ACd8c90c"
      }
    },
    {
      "to": "0xa731C23D7c95436Baaae9D52782f966E1ed07cc8",
      "value": "0",
      "data": null,
      "contractMethod": {
        "inputs": [
          {
            "internalType": "address",
            "name": "pool",
            "type": "address"
          },
          {
            "internalType": "address",
            "name": "recipient",
            "type": "address"
          }
        ],
        "name": "withdrawProtocolFees",
        "payable": false
      },
      "contractInputsValues": {
        "pool": "0x8e4e49b490e5228708be2cb59c0f0d2d3df290c0",
        "recipient": "0x693f30c37D5a0Db9258C636E93Ccf011ACd8c90c"
      }
    },
    {
      "to": "0xa731C23D7c95436Baaae9D52782f966E1ed07cc8",
      "value": "0",
      "data": null,
      "contractMethod": {
        "inputs": [
          {
            "internalType": "address",
            "name": "pool",
            "type": "address"
          },
          {
            "internalType": "address",
            "name": "recipient",
            "type": "address"
          }
        ],
        "name": "withdrawProtocolFees",
        "payable": false
      },
      "contractInputsValues": {
        "pool": "0x8edfb99c757c06bf8e8d3331698384b775ce80ca",
        "recipient": "0x693f30c37D5a0Db9258C636E93Ccf011ACd8c90c"
      }
    },
    {
      "to": "0xa731C23D7c95436Baaae9D52782f966E1ed07cc8",
      "value": "0",
      "data": null,
      "contractMethod": {
        "inputs": [
          {
            "internalType": "address",
            "name": "pool",
            "type": "address"
          },
          {
            "internalType": "address",
            "name": "recipient",
            "type": "address"
          }
        ],
        "name": "withdrawProtocolFees",
        "payable": false
      },
      "contractInputsValues": {
        "pool": "0x8ee5baf717fc5c49ffa65acefdcee886c3771026",
        "recipient": "0x693f30c37D5a0Db9258C636E93Ccf011ACd8c90c"
      }
    },
    {
      "to": "0xa731C23D7c95436Baaae9D52782f966E1ed07cc8",
      "value": "0",
      "data": null,
      "contractMethod": {
        "inputs": [
          {
            "internalType": "address",
            "name": "pool",
            "type": "address"
          },
          {
            "internalType": "address",
            "name": "recipient",
            "type": "address"
          }
        ],
        "name": "withdrawProtocolFees",
        "payable": false
      },
      "contractInputsValues": {
        "pool": "0x8f108324acce67f6a207d914ff83f5f16beb7552",
        "recipient": "0x693f30c37D5a0Db9258C636E93Ccf011ACd8c90c"
      }
    },
    {
      "to": "0xa731C23D7c95436Baaae9D52782f966E1ed07cc8",
      "value": "0",
      "data": null,
      "contractMethod": {
        "inputs": [
          {
            "internalType": "address",
            "name": "pool",
            "type": "address"
          },
          {
            "internalType": "address",
            "name": "recipient",
            "type": "address"
          }
        ],
        "name": "withdrawProtocolFees",
        "payable": false
      },
      "contractInputsValues": {
        "pool": "0x90a299cddeecb53afd8087960d11f90065a18128",
        "recipient": "0x693f30c37D5a0Db9258C636E93Ccf011ACd8c90c"
      }
    },
    {
      "to": "0xa731C23D7c95436Baaae9D52782f966E1ed07cc8",
      "value": "0",
      "data": null,
      "contractMethod": {
        "inputs": [
          {
            "internalType": "address",
            "name": "pool",
            "type": "address"
          },
          {
            "internalType": "address",
            "name": "recipient",
            "type": "address"
          }
        ],
        "name": "withdrawProtocolFees",
        "payable": false
      },
      "contractInputsValues": {
        "pool": "0x9130d476b52fbf9f2cff237af29a538bb0f048ff",
        "recipient": "0x693f30c37D5a0Db9258C636E93Ccf011ACd8c90c"
      }
    },
    {
      "to": "0xa731C23D7c95436Baaae9D52782f966E1ed07cc8",
      "value": "0",
      "data": null,
      "contractMethod": {
        "inputs": [
          {
            "internalType": "address",
            "name": "pool",
            "type": "address"
          },
          {
            "internalType": "address",
            "name": "recipient",
            "type": "address"
          }
        ],
        "name": "withdrawProtocolFees",
        "payable": false
      },
      "contractInputsValues": {
        "pool": "0x93d0b0a581a6c75eba5eec6ec6f0a5eb48cc2f4a",
        "recipient": "0x693f30c37D5a0Db9258C636E93Ccf011ACd8c90c"
      }
    },
    {
      "to": "0xa731C23D7c95436Baaae9D52782f966E1ed07cc8",
      "value": "0",
      "data": null,
      "contractMethod": {
        "inputs": [
          {
            "internalType": "address",
            "name": "pool",
            "type": "address"
          },
          {
            "internalType": "address",
            "name": "recipient",
            "type": "address"
          }
        ],
        "name": "withdrawProtocolFees",
        "payable": false
      },
      "contractInputsValues": {
        "pool": "0x944d4ae892de4bfd38742cc8295d6d5164c5593c",
        "recipient": "0x693f30c37D5a0Db9258C636E93Ccf011ACd8c90c"
      }
    },
    {
      "to": "0xa731C23D7c95436Baaae9D52782f966E1ed07cc8",
      "value": "0",
      "data": null,
      "contractMethod": {
        "inputs": [
          {
            "internalType": "address",
            "name": "pool",
            "type": "address"
          },
          {
            "internalType": "address",
            "name": "recipient",
            "type": "address"
          }
        ],
        "name": "withdrawProtocolFees",
        "payable": false
      },
      "contractInputsValues": {
        "pool": "0x94516edb148abae99cf35029417b765f421fa2cb",
        "recipient": "0x693f30c37D5a0Db9258C636E93Ccf011ACd8c90c"
      }
    },
    {
      "to": "0xa731C23D7c95436Baaae9D52782f966E1ed07cc8",
      "value": "0",
      "data": null,
      "contractMethod": {
        "inputs": [
          {
            "internalType": "address",
            "name": "pool",
            "type": "address"
          },
          {
            "internalType": "address",
            "name": "recipient",
            "type": "address"
          }
        ],
        "name": "withdrawProtocolFees",
        "payable": false
      },
      "contractInputsValues": {
        "pool": "0x94e9e7f4db9e5ee51ef6f29f5fbdac77c09e0a1e",
        "recipient": "0x693f30c37D5a0Db9258C636E93Ccf011ACd8c90c"
      }
    },
    {
      "to": "0xa731C23D7c95436Baaae9D52782f966E1ed07cc8",
      "value": "0",
      "data": null,
      "contractMethod": {
        "inputs": [
          {
            "internalType": "address",
            "name": "pool",
            "type": "address"
          },
          {
            "internalType": "address",
            "name": "recipient",
            "type": "address"
          }
        ],
        "name": "withdrawProtocolFees",
        "payable": false
      },
      "contractInputsValues": {
        "pool": "0x955e0a6cebc703f4f03de3654216fedee4681a26",
        "recipient": "0x693f30c37D5a0Db9258C636E93Ccf011ACd8c90c"
      }
    },
    {
      "to": "0xa731C23D7c95436Baaae9D52782f966E1ed07cc8",
      "value": "0",
      "data": null,
      "contractMethod": {
        "inputs": [
          {
            "internalType": "address",
            "name": "pool",
            "type": "address"
          },
          {
            "internalType": "address",
            "name": "recipient",
            "type": "address"
          }
        ],
        "name": "withdrawProtocolFees",
        "payable": false
      },
      "contractInputsValues": {
        "pool": "0x955e50e077ab81fafd40b84b1fa2be4257cd377a",
        "recipient": "0x693f30c37D5a0Db9258C636E93Ccf011ACd8c90c"
      }
    },
    {
      "to": "0xa731C23D7c95436Baaae9D52782f966E1ed07cc8",
      "value": "0",
      "data": null,
      "contractMethod": {
        "inputs": [
          {
            "internalType": "address",
            "name": "pool",
            "type": "address"
          },
          {
            "internalType": "address",
            "name": "recipient",
            "type": "address"
          }
        ],
        "name": "withdrawProtocolFees",
        "payable": false
      },
      "contractInputsValues": {
        "pool": "0x95901d8b49e14ae3bb19addcc7fe37d9a1d57d8a",
        "recipient": "0x693f30c37D5a0Db9258C636E93Ccf011ACd8c90c"
      }
    },
    {
      "to": "0xa731C23D7c95436Baaae9D52782f966E1ed07cc8",
      "value": "0",
      "data": null,
      "contractMethod": {
        "inputs": [
          {
            "internalType": "address",
            "name": "pool",
            "type": "address"
          },
          {
            "internalType": "address",
            "name": "recipient",
            "type": "address"
          }
        ],
        "name": "withdrawProtocolFees",
        "payable": false
      },
      "contractInputsValues": {
        "pool": "0x95f918c12edaf6ea1cd5ee98324d5a23ab08ab8f",
        "recipient": "0x693f30c37D5a0Db9258C636E93Ccf011ACd8c90c"
      }
    },
    {
      "to": "0xa731C23D7c95436Baaae9D52782f966E1ed07cc8",
      "value": "0",
      "data": null,
      "contractMethod": {
        "inputs": [
          {
            "internalType": "address",
            "name": "pool",
            "type": "address"
          },
          {
            "internalType": "address",
            "name": "recipient",
            "type": "address"
          }
        ],
        "name": "withdrawProtocolFees",
        "payable": false
      },
      "contractInputsValues": {
        "pool": "0x961ae4bb79e71f6f9820aacbdb9b742b54be789b",
        "recipient": "0x693f30c37D5a0Db9258C636E93Ccf011ACd8c90c"
      }
    },
    {
      "to": "0xa731C23D7c95436Baaae9D52782f966E1ed07cc8",
      "value": "0",
      "data": null,
      "contractMethod": {
        "inputs": [
          {
            "internalType": "address",
            "name": "pool",
            "type": "address"
          },
          {
            "internalType": "address",
            "name": "recipient",
            "type": "address"
          }
        ],
        "name": "withdrawProtocolFees",
        "payable": false
      },
      "contractInputsValues": {
        "pool": "0x962a84af56a285b9d7b22bb6337aa11cfd3b612c",
        "recipient": "0x693f30c37D5a0Db9258C636E93Ccf011ACd8c90c"
      }
    },
    {
      "to": "0xa731C23D7c95436Baaae9D52782f966E1ed07cc8",
      "value": "0",
      "data": null,
      "contractMethod": {
        "inputs": [
          {
            "internalType": "address",
            "name": "pool",
            "type": "address"
          },
          {
            "internalType": "address",
            "name": "recipient",
            "type": "address"
          }
        ],
        "name": "withdrawProtocolFees",
        "payable": false
      },
      "contractInputsValues": {
        "pool": "0x976614f648fa0fa38738ccc1d422d322eec7999d",
        "recipient": "0x693f30c37D5a0Db9258C636E93Ccf011ACd8c90c"
      }
    },
    {
      "to": "0xa731C23D7c95436Baaae9D52782f966E1ed07cc8",
      "value": "0",
      "data": null,
      "contractMethod": {
        "inputs": [
          {
            "internalType": "address",
            "name": "pool",
            "type": "address"
          },
          {
            "internalType": "address",
            "name": "recipient",
            "type": "address"
          }
        ],
        "name": "withdrawProtocolFees",
        "payable": false
      },
      "contractInputsValues": {
        "pool": "0x97fba08c586d182be8d168a39387f88971304ae2",
        "recipient": "0x693f30c37D5a0Db9258C636E93Ccf011ACd8c90c"
      }
    },
    {
      "to": "0xa731C23D7c95436Baaae9D52782f966E1ed07cc8",
      "value": "0",
      "data": null,
      "contractMethod": {
        "inputs": [
          {
            "internalType": "address",
            "name": "pool",
            "type": "address"
          },
          {
            "internalType": "address",
            "name": "recipient",
            "type": "address"
          }
        ],
        "name": "withdrawProtocolFees",
        "payable": false
      },
      "contractInputsValues": {
        "pool": "0x9893f9418890f3a4e33a072aae17e4d820b4de20",
        "recipient": "0x693f30c37D5a0Db9258C636E93Ccf011ACd8c90c"
      }
    },
    {
      "to": "0xa731C23D7c95436Baaae9D52782f966E1ed07cc8",
      "value": "0",
      "data": null,
      "contractMethod": {
        "inputs": [
          {
            "internalType": "address",
            "name": "pool",
            "type": "address"
          },
          {
            "internalType": "address",
            "name": "recipient",
            "type": "address"
          }
        ],
        "name": "withdrawProtocolFees",
        "payable": false
      },
      "contractInputsValues": {
        "pool": "0x991f9c46cfe183e919fa668dba3c9e785f8be350",
        "recipient": "0x693f30c37D5a0Db9258C636E93Ccf011ACd8c90c"
      }
    },
    {
      "to": "0xa731C23D7c95436Baaae9D52782f966E1ed07cc8",
      "value": "0",
      "data": null,
      "contractMethod": {
        "inputs": [
          {
            "internalType": "address",
            "name": "pool",
            "type": "address"
          },
          {
            "internalType": "address",
            "name": "recipient",
            "type": "address"
          }
        ],
        "name": "withdrawProtocolFees",
        "payable": false
      },
      "contractInputsValues": {
        "pool": "0x99215eb859110db1c6f90e6af0120f833f10e6b8",
        "recipient": "0x693f30c37D5a0Db9258C636E93Ccf011ACd8c90c"
      }
    },
    {
      "to": "0xa731C23D7c95436Baaae9D52782f966E1ed07cc8",
      "value": "0",
      "data": null,
      "contractMethod": {
        "inputs": [
          {
            "internalType": "address",
            "name": "pool",
            "type": "address"
          },
          {
            "internalType": "address",
            "name": "recipient",
            "type": "address"
          }
        ],
        "name": "withdrawProtocolFees",
        "payable": false
      },
      "contractInputsValues": {
        "pool": "0x992e0dbec5cf64c20b544f9a59f4af721ef78c28",
        "recipient": "0x693f30c37D5a0Db9258C636E93Ccf011ACd8c90c"
      }
    },
    {
      "to": "0xa731C23D7c95436Baaae9D52782f966E1ed07cc8",
      "value": "0",
      "data": null,
      "contractMethod": {
        "inputs": [
          {
            "internalType": "address",
            "name": "pool",
            "type": "address"
          },
          {
            "internalType": "address",
            "name": "recipient",
            "type": "address"
          }
        ],
        "name": "withdrawProtocolFees",
        "payable": false
      },
      "contractInputsValues": {
        "pool": "0x9ad28f6466270f7cd141facfdf3e110c64a9dfc0",
        "recipient": "0x693f30c37D5a0Db9258C636E93Ccf011ACd8c90c"
      }
    },
    {
      "to": "0xa731C23D7c95436Baaae9D52782f966E1ed07cc8",
      "value": "0",
      "data": null,
      "contractMethod": {
        "inputs": [
          {
            "internalType": "address",
            "name": "pool",
            "type": "address"
          },
          {
            "internalType": "address",
            "name": "recipient",
            "type": "address"
          }
        ],
        "name": "withdrawProtocolFees",
        "payable": false
      },
      "contractInputsValues": {
        "pool": "0x9b4bd4fd954bf49472a95a612195fe27eac6c2a4",
        "recipient": "0x693f30c37D5a0Db9258C636E93Ccf011ACd8c90c"
      }
    },
    {
      "to": "0xa731C23D7c95436Baaae9D52782f966E1ed07cc8",
      "value": "0",
      "data": null,
      "contractMethod": {
        "inputs": [
          {
            "internalType": "address",
            "name": "pool",
            "type": "address"
          },
          {
            "internalType": "address",
            "name": "recipient",
            "type": "address"
          }
        ],
        "name": "withdrawProtocolFees",
        "payable": false
      },
      "contractInputsValues": {
        "pool": "0x9b994ffab2fc50d139de7bc3faaff5acf16c8f90",
        "recipient": "0x693f30c37D5a0Db9258C636E93Ccf011ACd8c90c"
      }
    },
    {
      "to": "0xa731C23D7c95436Baaae9D52782f966E1ed07cc8",
      "value": "0",
      "data": null,
      "contractMethod": {
        "inputs": [
          {
            "internalType": "address",
            "name": "pool",
            "type": "address"
          },
          {
            "internalType": "address",
            "name": "recipient",
            "type": "address"
          }
        ],
        "name": "withdrawProtocolFees",
        "payable": false
      },
      "contractInputsValues": {
        "pool": "0x9bb86ed20ef3b84d52cbf9401e8c77677a372b0a",
        "recipient": "0x693f30c37D5a0Db9258C636E93Ccf011ACd8c90c"
      }
    },
    {
      "to": "0xa731C23D7c95436Baaae9D52782f966E1ed07cc8",
      "value": "0",
      "data": null,
      "contractMethod": {
        "inputs": [
          {
            "internalType": "address",
            "name": "pool",
            "type": "address"
          },
          {
            "internalType": "address",
            "name": "recipient",
            "type": "address"
          }
        ],
        "name": "withdrawProtocolFees",
        "payable": false
      },
      "contractInputsValues": {
        "pool": "0x9c9afa14267e1866677336487ef1eade072c8b50",
        "recipient": "0x693f30c37D5a0Db9258C636E93Ccf011ACd8c90c"
      }
    },
    {
      "to": "0xa731C23D7c95436Baaae9D52782f966E1ed07cc8",
      "value": "0",
      "data": null,
      "contractMethod": {
        "inputs": [
          {
            "internalType": "address",
            "name": "pool",
            "type": "address"
          },
          {
            "internalType": "address",
            "name": "recipient",
            "type": "address"
          }
        ],
        "name": "withdrawProtocolFees",
        "payable": false
      },
      "contractInputsValues": {
        "pool": "0x9ccd4b149f067864118f0290188d832fd3405e75",
        "recipient": "0x693f30c37D5a0Db9258C636E93Ccf011ACd8c90c"
      }
    },
    {
      "to": "0xa731C23D7c95436Baaae9D52782f966E1ed07cc8",
      "value": "0",
      "data": null,
      "contractMethod": {
        "inputs": [
          {
            "internalType": "address",
            "name": "pool",
            "type": "address"
          },
          {
            "internalType": "address",
            "name": "recipient",
            "type": "address"
          }
        ],
        "name": "withdrawProtocolFees",
        "payable": false
      },
      "contractInputsValues": {
        "pool": "0x9d400e457bbe5fd0594513bf1ef4a3a3d31f7c40",
        "recipient": "0x693f30c37D5a0Db9258C636E93Ccf011ACd8c90c"
      }
    },
    {
      "to": "0xa731C23D7c95436Baaae9D52782f966E1ed07cc8",
      "value": "0",
      "data": null,
      "contractMethod": {
        "inputs": [
          {
            "internalType": "address",
            "name": "pool",
            "type": "address"
          },
          {
            "internalType": "address",
            "name": "recipient",
            "type": "address"
          }
        ],
        "name": "withdrawProtocolFees",
        "payable": false
      },
      "contractInputsValues": {
        "pool": "0x9ed2f41a8c6cbaa2154a71de56c18dd78aa40469",
        "recipient": "0x693f30c37D5a0Db9258C636E93Ccf011ACd8c90c"
      }
    },
    {
      "to": "0xa731C23D7c95436Baaae9D52782f966E1ed07cc8",
      "value": "0",
      "data": null,
      "contractMethod": {
        "inputs": [
          {
            "internalType": "address",
            "name": "pool",
            "type": "address"
          },
          {
            "internalType": "address",
            "name": "recipient",
            "type": "address"
          }
        ],
        "name": "withdrawProtocolFees",
        "payable": false
      },
      "contractInputsValues": {
        "pool": "0x9fc87e8c21ac11826194547bd85f1df6a11e5613",
        "recipient": "0x693f30c37D5a0Db9258C636E93Ccf011ACd8c90c"
      }
    },
    {
      "to": "0xa731C23D7c95436Baaae9D52782f966E1ed07cc8",
      "value": "0",
      "data": null,
      "contractMethod": {
        "inputs": [
          {
            "internalType": "address",
            "name": "pool",
            "type": "address"
          },
          {
            "internalType": "address",
            "name": "recipient",
            "type": "address"
          }
        ],
        "name": "withdrawProtocolFees",
        "payable": false
      },
      "contractInputsValues": {
        "pool": "0xa08e8e9e24577f7b71baba5ef6788cd7c7bfd44c",
        "recipient": "0x693f30c37D5a0Db9258C636E93Ccf011ACd8c90c"
      }
    },
    {
      "to": "0xa731C23D7c95436Baaae9D52782f966E1ed07cc8",
      "value": "0",
      "data": null,
      "contractMethod": {
        "inputs": [
          {
            "internalType": "address",
            "name": "pool",
            "type": "address"
          },
          {
            "internalType": "address",
            "name": "recipient",
            "type": "address"
          }
        ],
        "name": "withdrawProtocolFees",
        "payable": false
      },
      "contractInputsValues": {
        "pool": "0xa10e4356abca753558120b1717dc2159b3528479",
        "recipient": "0x693f30c37D5a0Db9258C636E93Ccf011ACd8c90c"
      }
    },
    {
      "to": "0xa731C23D7c95436Baaae9D52782f966E1ed07cc8",
      "value": "0",
      "data": null,
      "contractMethod": {
        "inputs": [
          {
            "internalType": "address",
            "name": "pool",
            "type": "address"
          },
          {
            "internalType": "address",
            "name": "recipient",
            "type": "address"
          }
        ],
        "name": "withdrawProtocolFees",
        "payable": false
      },
      "contractInputsValues": {
        "pool": "0xa12c15bc609b2442a53263e517ac5e9bf6e024d5",
        "recipient": "0x693f30c37D5a0Db9258C636E93Ccf011ACd8c90c"
      }
    },
    {
      "to": "0xa731C23D7c95436Baaae9D52782f966E1ed07cc8",
      "value": "0",
      "data": null,
      "contractMethod": {
        "inputs": [
          {
            "internalType": "address",
            "name": "pool",
            "type": "address"
          },
          {
            "internalType": "address",
            "name": "recipient",
            "type": "address"
          }
        ],
        "name": "withdrawProtocolFees",
        "payable": false
      },
      "contractInputsValues": {
        "pool": "0xa28507ec2d01530556f412c8ef0aa5d440a46ffc",
        "recipient": "0x693f30c37D5a0Db9258C636E93Ccf011ACd8c90c"
      }
    },
    {
      "to": "0xa731C23D7c95436Baaae9D52782f966E1ed07cc8",
      "value": "0",
      "data": null,
      "contractMethod": {
        "inputs": [
          {
            "internalType": "address",
            "name": "pool",
            "type": "address"
          },
          {
            "internalType": "address",
            "name": "recipient",
            "type": "address"
          }
        ],
        "name": "withdrawProtocolFees",
        "payable": false
      },
      "contractInputsValues": {
        "pool": "0xa2dbb49e6de4ccdb80146e2e2d532d173a7c487f",
        "recipient": "0x693f30c37D5a0Db9258C636E93Ccf011ACd8c90c"
      }
    },
    {
      "to": "0xa731C23D7c95436Baaae9D52782f966E1ed07cc8",
      "value": "0",
      "data": null,
      "contractMethod": {
        "inputs": [
          {
            "internalType": "address",
            "name": "pool",
            "type": "address"
          },
          {
            "internalType": "address",
            "name": "recipient",
            "type": "address"
          }
        ],
        "name": "withdrawProtocolFees",
        "payable": false
      },
      "contractInputsValues": {
        "pool": "0xa370168674a123f8df057d722d14011b26a96e8b",
        "recipient": "0x693f30c37D5a0Db9258C636E93Ccf011ACd8c90c"
      }
    },
    {
      "to": "0xa731C23D7c95436Baaae9D52782f966E1ed07cc8",
      "value": "0",
      "data": null,
      "contractMethod": {
        "inputs": [
          {
            "internalType": "address",
            "name": "pool",
            "type": "address"
          },
          {
            "internalType": "address",
            "name": "recipient",
            "type": "address"
          }
        ],
        "name": "withdrawProtocolFees",
        "payable": false
      },
      "contractInputsValues": {
        "pool": "0xa3a56e56b9b954d1725e57eb886cd9f8e4f6a7ba",
        "recipient": "0x693f30c37D5a0Db9258C636E93Ccf011ACd8c90c"
      }
    }
  ]
}